LICENSE
README.md
setup.py
lineus/__init__.py
lineus/diagnostics.py
lineus/lineus.py
lineus/test_lineus.py
lineus.egg-info/PKG-INFO
lineus.egg-info/SOURCES.txt
lineus.egg-info/dependency_links.txt
lineus.egg-info/requires.txt
lineus.egg-info/top_level.txt