Metadata-Version: 2.1
Name: lineus
Version: 1.0.3
Summary: The Python module for Line-us
Home-page: https://github.com/Line-us/LineUsPythonModule
Author: Robert Poll
Author-email: rob@line-us.com
License: MIT
Keywords: Line-us lineus drawing robot
Platform: UNKNOWN
License-File: LICENSE
